src/__init__.py
src/client/__init__.py
src/client/configuration.py
src/client/legacy_account_api.py
src/client/legacy_api_access_token_api.py
src/client/legacy_authorization_api.py
src/client/legacy_aws_config_api.py
src/client/legacy_aws_role_api.py
src/client/legacy_base_storage_config_api.py
src/client/legacy_cloud_config_api.py
src/client/legacy_connection_api.py
src/client/legacy_connection_permission_api.py
src/client/legacy_connector_metadata_api.py
src/client/legacy_environment_parameter_api.py
src/client/legacy_flow_api.py
src/client/legacy_flow_node_api.py
src/client/legacy_flow_notification_settings_api.py
src/client/legacy_flow_permission_api.py
src/client/legacy_flow_run_api.py
src/client/legacy_flow_run_parameter_override_api.py
src/client/legacy_folder_api.py
src/client/legacy_imported_dataset_api.py
src/client/legacy_job_api.py
src/client/legacy_job_group_api.py
src/client/legacy_macro_api.py
src/client/legacy_misc_api.py
src/client/legacy_o_auth2_api_token_api.py
src/client/legacy_output_object_api.py
src/client/legacy_person_api.py
src/client/legacy_plan_api.py
src/client/legacy_plan_edge_api.py
src/client/legacy_plan_node_api.py
src/client/legacy_plan_override_api.py
src/client/legacy_plan_snapshot_run_api.py
src/client/legacy_publication_api.py
src/client/legacy_schedule_api.py
src/client/legacy_sql_script_api.py
src/client/legacy_webhook_flow_task_api.py
src/client/legacy_workspace_api.py
src/client/legacy_wrangled_dataset_api.py
src/client/legacy_write_setting_api.py
src/client/person_api.py
src/client/plan_api.py
src/client/plan_edge_api.py
src/client/plan_node_api.py
src/client/plan_override_api.py
src/client/plan_snapshot_run_api.py
src/client/schedule_api.py
src/client/workflows_api.py
src/client/workspace_api.py
src/client/api/__init__.py
src/client/api/api_client.py
src/client/api/oauth2_handler.py
src/client/api/rest.py
src/client/iam_models/__init__.py
src/client/iam_models/any_ofperson_id.py
openone-0.1.3.dist-info/METADATA
openone-0.1.3.dist-info/WHEEL
openone-0.1.3.dist-info/entry_points.txt
openone-0.1.3.dist-info/licenses/LICENSE
openone-0.1.3.dist-info/RECORD
