Metadata-Version: 2.4
Name: OpenOne
Version: 0.1.3
Summary: Model Context Protocol (MCP) server for Alteryx Analytics Cloud
Author-email: Jupiter Bakakeu <jupiter.bakakeu@gmail.com>
License: MIT
License-File: LICENSE
Keywords: alteryx,analytics-cloud,mcp,model-context-protocol
Classifier: Development Status :: 3 - Alpha
Classifier: Intended Audience :: Developers
Classifier: License :: OSI Approved :: MIT License
Classifier: Programming Language :: Python :: 3
Classifier: Programming Language :: Python :: 3.10
Classifier: Programming Language :: Python :: 3.11
Classifier: Programming Language :: Python :: 3.12
Classifier: Topic :: Software Development :: Libraries :: Python Modules
Requires-Python: >=3.10
Requires-Dist: certifi>=14.05.14
Requires-Dist: click>=8.1.7
Requires-Dist: fastmcp
Requires-Dist: python-dateutil>=2.5.3
Requires-Dist: requests>=2.28.1
Requires-Dist: six>=1.10
Requires-Dist: urllib3>=1.15.1
Provides-Extra: dev
Requires-Dist: build>=1.2.2.post1; extra == 'dev'
Requires-Dist: pytest-asyncio>=0.21.0; extra == 'dev'
Requires-Dist: pytest>=7.0.0; extra == 'dev'
Requires-Dist: twine>=6.1.0; extra == 'dev'
